{"commitInfo":{"timestamp":1777669994228,"operation":"WRITE","operationParameters":{"mode":"Overwrite"},"engineInfo":"delta-rs:py-1.5.1","clientVersion":"delta-rs.py-1.5.1","operationMetrics":{"execution_time_ms":1,"num_added_files":1,"num_added_rows":113,"num_partitions":0,"num_removed_files":0}}}
{"protocol":{"minReaderVersion":1,"minWriterVersion":2}}
{"metaData":{"id":"4fbffec6-e94c-48a9-bc8f-eac73f15affe","name":null,"description":null,"format":{"provider":"parquet","options":{}},"schemaString":"{\"type\":\"struct\",\"fields\":[{\"name\":\"lei\",\"type\":\"string\",\"nullable\":true,\"metadata\":{}},{\"name\":\"exposure_type\",\"type\":\"string\",\"nullable\":true,\"metadata\":{}},{\"name\":\"as_of_date\",\"type\":\"date\",\"nullable\":true,\"metadata\":{}},{\"name\":\"exposure_count\",\"type\":\"integer\",\"nullable\":true,\"metadata\":{}},{\"name\":\"total_amount_eur\",\"type\":\"double\",\"nullable\":true,\"metadata\":{}},{\"name\":\"total_rwa_eur\",\"type\":\"double\",\"nullable\":true,\"metadata\":{}}]}","partitionColumns":[],"createdTime":1777669994227,"configuration":{}}}
{"add":{"path":"part-00000-aa4eb417-4dea-4023-a814-816344ddb2a8-c000.snappy.parquet","partitionValues":{},"size":4440,"modificationTime":1777669994228,"dataChange":true,"stats":"{\"numRecords\":113,\"minValues\":{\"exposure_type\":\"DEBT_SECURITY\",\"as_of_date\":\"2026-03-31\",\"exposure_count\":1,\"total_amount_eur\":-35394968.92,\"total_rwa_eur\":-49871321.89,\"lei\":\"99990000000000000000\"},\"maxValues\":{\"exposure_type\":\"OFF_BALANCE_SHEET\",\"exposure_count\":4,\"total_rwa_eur\":92894997.323,\"as_of_date\":\"2026-03-31\",\"lei\":\"99990000000000000049\",\"total_amount_eur\":164571138.66},\"nullCount\":{\"lei\":0,\"exposure_count\":0,\"exposure_type\":0,\"total_amount_eur\":0,\"as_of_date\":0,\"total_rwa_eur\":0}}","tags":null,"baseRowId":null,"defaultRowCommitVersion":null,"clusteringProvider":null}}